frontx/__init__.py
frontx/_boltzmann.py
frontx/_util.py
frontx/models.py
frontx-0.1.0.dist-info/WHEEL
frontx-0.1.0.dist-info/METADATA
frontx-0.1.0.dist-info/RECORD
